stochax/__init__.py
stochax/brownian_motion.py
stochax/calibration_results.py
stochax/core.py
stochax/mean_reverting.py
stochax-0.2.0.dist-info/LICENSE
stochax-0.2.0.dist-info/METADATA
stochax-0.2.0.dist-info/WHEEL
stochax-0.2.0.dist-info/top_level.txt
stochax-0.2.0.dist-info/RECORD
