Metadata-Version: 2.2
Name: stochax
Version: 0.2.0
Author-email: agdiiura <andreadiiura@gmail.com>
License: MIT License
Project-URL: Homepage, https://github.com/agdiiura/stochax
Project-URL: Documentation, https://stochax.readthedocs.io/en/stable/index.html
Project-URL: Repository, https://github.com/agdiiura/stochax.git
License-File: LICENSE
Requires-Dist: joblib>=1.3.2
Requires-Dist: pandas>=2.2.1
Requires-Dist: numpy>=1.26.0
Requires-Dist: plotly>=5.20.0
Requires-Dist: scikit-learn>=1.4.0
Requires-Dist: scipy>=1.12.0
Requires-Dist: arch>=6.3.0
Requires-Dist: pydantic>=2.5.0
Requires-Dist: polars>=1.14.0
Provides-Extra: build
Requires-Dist: ruff>=0.9.0; extra == "build"
Requires-Dist: colorama>=0.4.6; extra == "build"
Requires-Dist: coverage>=7.0; extra == "build"
Requires-Dist: isort>=5.12.0; extra == "build"
Requires-Dist: pre-commit>=3.3.0; extra == "build"
Requires-Dist: setuptools-git-versioning>=1.13.4; extra == "build"
Requires-Dist: unittest-xml-reporting>=3.2.0; extra == "build"
Requires-Dist: tqdm>=4.66.5; extra == "build"
Provides-Extra: docs
Requires-Dist: mkdocs>=1.6.0; extra == "docs"
Requires-Dist: mkdocstrings[python]>=0.25.0; extra == "docs"
